{
  "required": true,
  "minVersion": "0.8",
  "package": "tfc.tingedlights.mixin",
  "compatibilityLevel": "JAVA_17",
  "refmap": "tingedlights.refmap.json",
  "mixins": [
  ],
  "client": [
    "MojangWhy",
    "backend.BlockMixin",
    "backend.ClientLevelMixin",
    "backend.LevelChunkMixin",
    "backend.LevelLightEngineMixin",
    "backend.LevelMixin",
    "backend.SectionChangedPacketMixin",
    "jank.IForgeVertexConsumerMixin",
    "render.BlockRendererMixin",
    "render.FluidRendererMixin",
    "render.LevelRendererMixin",
    "render.multibuffers.BufferSourceMixin",
    "render.others.BlockEntityRendererMixin",
    "render.others.EntityRendererMixin",
    "render.others.FirstPersonHandMixin",
    "render.others.LightingMixin",
    "render.others.ParticleEngineMixin",
    "render.shaders.ShaderInstanceMixin",
    "render.shaders.ShaderInstancePreprocessorMixin",
    "render.shaders.ShaderProgramMixin",
    "render.vertex.VertexElementMixin",
    "render.vertex.VertexFormatMixin",
    "render.vertex.builder.BufferBuilderMixin",
    "render.vertex.builder.VertexBufferConsumerMixin"
  ],
  "injectors": {
    "defaultRequire": 1
  }
}
